setup.py
flaskcli/__init__.py
flaskcli/flaskcli.py
flaskcli.egg-info/PKG-INFO
flaskcli.egg-info/SOURCES.txt
flaskcli.egg-info/dependency_links.txt
flaskcli.egg-info/requires.txt
flaskcli.egg-info/top_level.txt